sphinx_thumb_image/__init__.py
sphinx_thumb_image/directives.py
sphinx_thumb_image/lib.py
sphinx_thumb_image/resize.py
sphinx_thumb_image-0.4.0.dist-info/METADATA
sphinx_thumb_image-0.4.0.dist-info/WHEEL
sphinx_thumb_image-0.4.0.dist-info/licenses/COPYING
sphinx_thumb_image-0.4.0.dist-info/licenses/LICENSE
sphinx_thumb_image-0.4.0.dist-info/RECORD
