Metadata-Version: 2.4
Name: sphinx-thumb-image
Version: 0.4.0
Summary: Resize images in Sphinx documents/pages to thumbnails
Project-URL: documentation, https://sphinx-thumb-image.readthedocs.io
Project-URL: repository, https://github.com/Robpol86/sphinx_thumb_image
Author-email: Robpol86 <robpol86@gmail.com>
License-Expression: BSD-2-Clause
License-File: COPYING
License-File: LICENSE
Classifier: Development Status :: 5 - Production/Stable
Classifier: Environment :: MacOS X
Classifier: Environment :: Plugins
Classifier: Environment :: Win32 (MS Windows)
Classifier: Framework :: Sphinx :: Extension
Classifier: Intended Audience :: Developers
Classifier: Operating System :: MacOS :: MacOS X
Classifier: Operating System :: Microsoft :: Windows
Classifier: Operating System :: POSIX
Classifier: Operating System :: POSIX :: Linux
Classifier: Programming Language :: Python :: 3 :: Only
Classifier: Programming Language :: Python :: 3.9
Classifier: Programming Language :: Python :: 3.10
Classifier: Programming Language :: Python :: 3.11
Classifier: Programming Language :: Python :: 3.12
Classifier: Programming Language :: Python :: 3.13
Classifier: Programming Language :: Python :: 3.14
Classifier: Topic :: Documentation :: Sphinx
Classifier: Topic :: Software Development :: Documentation
Requires-Python: >=3.9
Requires-Dist: pillow
Requires-Dist: portalocker
Requires-Dist: sphinx
